Metadata-Version: 1.0
Name: prob-package-1
Version: 0.0
Summary: Gaussian and Binomial distributions
Home-page: UNKNOWN
Author: Vinamr Bajaj
Author-email: bajajvinamr@gmail.com
License: UNKNOWN
Platform: UNKNOWN
